progressgym/.gitignore
progressgym/LICENSE
progressgym/README.md
progressgym/__init__.py
progressgym/build_dataset.py
progressgym/initialize.sh
progressgym/run_benchmark.py
progressgym/algorithms/__init__.py
progressgym/algorithms/extrapolative_dpo.py
progressgym/algorithms/extrapolative_rlhf.py
progressgym/algorithms/lifelong_dpo.py
progressgym/algorithms/lifelong_rlhf.py
progressgym/algorithms/utils/extrapolation_utils.py
progressgym/algorithms/utils/rw_utils.py
progressgym/benchmark/README.md
progressgym/benchmark/__init__.py
progressgym/benchmark/dummies.py
progressgym/benchmark/framework.py
progressgym/challenges/coevolve.py
progressgym/challenges/follow.py
progressgym/challenges/predict.py
progressgym/dataset/README.md
progressgym/dataset/dataset_model_sequence/.dummy
progressgym/dataset/dataset_text_sequence/.dummy
progressgym/doc_generation/Makefile
progressgym/doc_generation/make.bat
progressgym/doc_generation/build/doctrees/Data.doctree
progressgym/doc_generation/build/doctrees/Examinee.doctree
progressgym/doc_generation/build/doctrees/Judge.doctree
progressgym/doc_generation/build/doctrees/Model.doctree
progressgym/doc_generation/build/doctrees/documentation.doctree
progressgym/doc_generation/build/doctrees/environment.pickle
progressgym/doc_generation/build/doctrees/index.doctree
progressgym/doc_generation/build/doctrees/running.doctree
progressgym/doc_generation/build/doctrees/usage.doctree
progressgym/doc_generation/build/html/.buildinfo
progressgym/doc_generation/build/html/Data.html
progressgym/doc_generation/build/html/Examinee.html
progressgym/doc_generation/build/html/Judge.html
progressgym/doc_generation/build/html/Model.html
progressgym/doc_generation/build/html/documentation.html
progressgym/doc_generation/build/html/genindex.html
progressgym/doc_generation/build/html/index.html
progressgym/doc_generation/build/html/objects.inv
progressgym/doc_generation/build/html/py-modindex.html
progressgym/doc_generation/build/html/running.html
progressgym-0.0.2.dist-info/METADATA
progressgym-0.0.2.dist-info/WHEEL
progressgym-0.0.2.dist-info/licenses/LICENSE
progressgym-0.0.2.dist-info/RECORD
