Metadata-Version: 2.3
Name: ProgressGym
Version: 0.0.2
Summary: alpha
Project-URL: Documentation, https://pku-alignment.github.io/ProgressGym/
Project-URL: Github, https://github.com/PKU-Alignment/ProgressGym
Author-email: "Tianyi Qiu, Yang Zhang, Xuchuan Huang, Jasmine Xinze Li" <2200013216@stu.pku.edu.cn>
License-Expression: MIT
License-File: LICENSE
Classifier: License :: OSI Approved :: MIT License
Classifier: Operating System :: OS Independent
Classifier: Programming Language :: Python :: 3
Requires-Python: >=3.8
Requires-Dist: argparse
Requires-Dist: bs4
Requires-Dist: deepspeed
Requires-Dist: gensim
Requires-Dist: guidance
Requires-Dist: jsonstreamer
Requires-Dist: levenshtein
Requires-Dist: lxml
Requires-Dist: nltk
Requires-Dist: numpy
Requires-Dist: pandas
Requires-Dist: ray
Requires-Dist: seaborn
Requires-Dist: tqdm
Requires-Dist: transformers==4.40.0
Requires-Dist: trl
Requires-Dist: vllm>0.4.0
Requires-Dist: wheel
Requires-Dist: yajl
